[
    {
      "Title": "The Thing",
      "Released": "1982-06-27",
      "Runtime": 109,
      "Genres": [
        "Horror",
        "Mystery",
        "Sci-Fi"
      ],
      "Directors": [
        "John Carpenter"
      ],
      "Writers": [
        "Bill Lancaster, John W. Campbell Jr."
      ],
      "Actors": [
        "Kurt Russell",
        "Wilford Brimley",
        "Keith David"
      ],
      "Plot": "A research team in Antarctica is hunted by a shape-shifting alien that assumes the appearance of its victims.",
      "Poster": "https://m.media-amazon.com/images/M/MV5BNGViZWZmM2EtNGYzZi00ZDAyLTk3ODMtNzIyZTBjN2Y1NmM1XkEyXkFqcGdeQXVyNTAyODkwOQ@@._V1_SX300.jpg",
      "Metascore": 57,
      "imdbRating": 8.2
    },
    {
      "Title": "Akira",
      "Released": "1991-06-27",
      "Runtime": 124,
      "Genres": [
        "Animation",
        "Action",
        "Drama"
      ],
      "Directors": [
        "Katsuhiro Ôtomo"
      ],
      "Writers": [
        "Katsuhiro Ôtomo",
        "Izô Hashimoto"
      ],
      "Actors": [
        "Mitsuo Iwata",
        "Nozomu Sasaki",
        "Mami Koyama"
      ],
      "Plot": "A secret military project endangers Neo-Tokyo when it turns a biker gang member into a rampaging psychic psychopath who can only be stopped by a teenager, his gang of biker friends and a group of psychics.",
      "Poster": "https://m.media-amazon.com/images/M/MV5BM2ZiZTk1ODgtMTZkNS00NTYxLWIxZTUtNWExZGYwZTRjODViXkEyXkFqcGdeQXVyMTE2MzA3MDM@._V1_SX300.jpg",
      "Metascore": 67,
      "imdbRating": 8
    },
    {
      "Title": "A Silent Voice",
      "Released": "2003-07-08",
      "Runtime": 3,
      "Genres": [
        "Short"
      ],
      "Directors": [
        "Milad Mohebian"
      ],
      "Writers": [
        "N/A"
      ],
      "Actors": [
        "N/A"
      ],
      "Plot": "A silent voice is for voices that are not heard before! For people who die in silence! And the only voice that they hear is the Fire sound.",
      "Poster": "https://m.media-amazon.com/images/M/MV5BOGNkNjgzNWYtNjcyOC00Y2Y3LWI5NWUtOGViMDNmNzg4NGM1XkEyXkFqcGdeQXVyNjI0Nzc1NTM@._V1_SX300.jpg",
      "Metascore": 54,
      "imdbRating": 4.1
    },
    {
      "Title": "Pirates of the Caribbean: The Curse of the Black Pearl",
      "Released": "2003-07-08",
      "Runtime": 143,
      "Genres": [
        "Action",
        "Adventure",
        "Fantasy"
      ],
      "Directors": [
        "Gore Verbinski"
      ],
      "Writers": [
        "Ted Elliott",
        "Terry Rossio",
        "Stuart Beattie"
      ],
      "Actors": [
        "Johnny Depp",
        "Geoffrey Rush",
        "Orlando Bloom"
      ],
      "Plot": "Blacksmith Will Turner teams up with eccentric pirate \"Captain\" Jack Sparrow to save his love, the governor's daughter, from Jack's former pirate allies, who are now undead.",
      "Poster": "https://m.media-amazon.com/images/M/MV5BNGYyZGM5MGMtYTY2Ni00M2Y1LWIzNjQtYWUzM2VlNGVhMDNhXkEyXkFqcGdeQXVyMTMxODk2OTU@._V1_SX300.jpg",
      "Metascore": 63,
      "imdbRating": 8.1
    }
  ]